flypaper/__init__.py
flypaper/consent.py
flypaper/report.py
flypaper/system_information.py
flypaper/test_consent.py
flypaper/test_system_information.py
flypaper-0.1.1.dist-info/METADATA
flypaper-0.1.1.dist-info/WHEEL
flypaper-0.1.1.dist-info/top_level.txt
flypaper-0.1.1.dist-info/RECORD
