Metadata-Version: 2.1
Name: flypaper
Version: 0.1.1
Summary: Flypaper: Do you build developer tools? Flypaper helps you know your users.
Home-page: https://github.com/bugout-dev/flypaper
Author: Bugout.dev
Author-email: engineering@bugout.dev
License: UNKNOWN
Platform: UNKNOWN
Classifier: Development Status :: 3 - Alpha
Classifier: Programming Language :: Python
Classifier: License :: OSI Approved :: Apache Software License
Classifier: Topic :: Software Development :: Libraries
Requires-Dist: bugout
Provides-Extra: dev
Requires-Dist: black ; extra == 'dev'
Requires-Dist: mypy ; extra == 'dev'
Requires-Dist: wheel ; extra == 'dev'
Provides-Extra: distribute
Requires-Dist: setuptools ; extra == 'distribute'
Requires-Dist: twine ; extra == 'distribute'
Requires-Dist: wheel ; extra == 'distribute'
